devtools_unit/__init__.py
devtools_unit-1.0.1.dist-info/METADATA
devtools_unit-1.0.1.dist-info/WHEEL
devtools_unit-1.0.1.dist-info/top_level.txt
devtools_unit-1.0.1.dist-info/RECORD
