Metadata-Version: 2.1
Name: devtools-unit
Version: 1.0.1
Summary: Unit converter
Home-page: https://devtools.at/tools/unit-converter
Author: DevTools.at
Author-email: hello@devtools.at
Project-URL: Homepage, https://devtools.at/tools/unit-converter
Project-URL: Repository, https://github.com/devtools-at/unit-converter
Classifier: Development Status :: 4 - Beta
Classifier: Intended Audience :: Developers
Classifier: License :: OSI Approved :: MIT License
Classifier: Programming Language :: Python :: 3
Requires-Python: >=3.8
